<?xml version="1.0"?>
<aid:doc xmlns:aid="http://ns.adobe.com/AdobeInDesign/4.0/"><h1>第1章　ちょっと休憩（それとダークマターの話）</h1>
<?dtp level="1" section="第1章　ちょっと休憩（それとダークマターの話）"?>
<h2>1.1　ダークマターって？</h2>
<?dtp level="2" section="1.1　ダークマターって？"?>
<p>ある日のダンスレッスン中。しばらくへろへろとした動きを続けていた篠澤さんは、案の定、ステップの途中でばったり倒れ込んで動かなくなった。</p>
<p>「……一応聞きますけど、大丈夫ですか？」</p>
<p>もはやこの程度では動揺しない自分が怖い。当の篠澤さんは、床に顔を伏せたまま、くぐもった声で答えた。</p>
<p>「だめ。ダークマターがぶつかって来たみたい」</p>
<p>「見えない相手にも負けるとは……名人芸ですね！」</p>
<p>大げさに驚いてみせると、篠澤さんは顔を上げ、意外そうな表情を見せた。</p>
<p>「ダークマター、知ってるんだ」</p>
<p>「ここ最近、物理の知識でマウントを取られてますからね。次に言い出しそうなネタをざっと勉強しました」</p>
<p>「じゃあ、どういうものか言ってみて」</p>
<p>「日本語で暗黒物質。目に見えない謎の物質で、宇宙に満ちあふれてる──とか」</p>
<p>「全然だめ。情報量が少ない。92点」</p>
<p>「……絶妙に高評価なのはなぜです？」</p>
<p>「そうやっていつも私に話す余白をくれる。プロデューサー、よくわかってる。そういうところが好き」</p>
<p>魅惑的な笑みに、思わず視線を奪われる。</p>
<p>やはり俺の判断は間違っていなかった。篠澤さんが有名なアイドルになれば、こういう唐突な表情に、虜になるファンは多いことだろう。</p>
<p>……これで床にうつ伏せじゃなければ、完璧なんだけど。</p>
<h4>観測的証拠</h4>
<?dtp level="4" section="観測的証拠"?>
<p>上体を起こした篠澤さんが、壁にもたれかかって座る。</p>
<p>なんだかんだ言いながら、結局こうして篠澤さんの休憩に付き合ってしまう。俺もまだまだ甘い。</p>
<p>「そもそも、ダークマターって本当にあるんですか？　直接は観測できないなら、幽霊の存在を証明するみたいな話じゃありません？」</p>
<p>「全然違う。証拠はいろいろあるよ。例えば……」</p>
<p>そう言ってよろよろと立ち上がると、ホワイトボードに箇条書きしながら説明を始めた。（レビュー：<span type="bibno">[1] </span>の27章周辺）</p>
<list current_no="1" total_no="3">銀河の回転曲線: 星の周回速度を測り、見える星から推定される重力と比較する。光らない『ダークな』物質が大量にないと、測定された速度を説明できない。</list>
<list current_no="2" total_no="3">宇宙マイクロ波背景放射（CMB）: 宇宙の全方向から来る微弱な電波の温度ゆらぎを調べる。ダークマターを含む<inlineequation><Image href="file://images/_review_math/_gen_4e73a24d6dbb26ffc7286927b7452dfaae09dbed05a0d0c38adab081c78d96fe.pdf" type="inline"/></inlineequation>-CDM模型<footnote><inlineequation><Image href="file://images/_review_math/_gen_4e73a24d6dbb26ffc7286927b7452dfaae09dbed05a0d0c38adab081c78d96fe.pdf" type="inline"/></inlineequation>-CDM模型の“CDM”は『冷たいダークマター』の意味。<inlineequation><Image href="file://images/_review_math/_gen_4e73a24d6dbb26ffc7286927b7452dfaae09dbed05a0d0c38adab081c78d96fe.pdf" type="inline"/></inlineequation>は別の成分で、いわゆるダークエネルギー。この二つの正体不明な成分が、宇宙の全エネルギーの約95%を占めてる。すごく理不尽で、わくわくするね。</footnote>で、角相関が精度よく説明できる。</list>
<list current_no="3" total_no="3">その他: 宇宙の大規模構造、バリオン音響振動（BAO）、重力レンズ効果、など。</list>
<p>「……CMB？　<inlineequation><Image href="file://images/_review_math/_gen_4e73a24d6dbb26ffc7286927b7452dfaae09dbed05a0d0c38adab081c78d96fe.pdf" type="inline"/></inlineequation>-CDM模型？」</p>
<p>「まず、宇宙が始まってから約38万年の間に──」</p>
<p>「待ってください、いきなりスケールがデカすぎです」</p>
<p>「……ビッグバン後の宇宙の膨張史を説明する、いまのところ最有力の宇宙論模型が、<inlineequation><Image href="file://images/_review_math/_gen_4e73a24d6dbb26ffc7286927b7452dfaae09dbed05a0d0c38adab081c78d96fe.pdf" type="inline"/></inlineequation>-CDM模型。宇宙の全方向から来る電波のことをCMBと呼ぶけど、それだけじゃなく、いろんな観測をまとめて説明できる。そこから話す？」</p>
<p>「長くなりそうなので、その話はまた今度に」</p>
<h4>性質</h4>
<?dtp level="4" section="性質"?>
<p>「ダークマターって、身の周りにもあるんですか？」</p>
<p>「うん。むしろ、ダークマターがなければ私たちは存在しない。最初にダークマターが集まり、その重力に引き寄せられた物質が銀河を作った。ダークマターが先、私たちは後」</p>
<p>「なかなか常識を覆しますね。具体的には、どのくらいあるんですか？」</p>
<p>「<inlineequation><Image href="file://images/_review_math/_gen_dd1354afdd4444c042bae6dcea6b7d5c47f731b7aa662016c30c98941687ee70.pdf" type="inline"/></inlineequation>くらい。地球全体だと、牛乳パック一つ分の重さ」</p>
<p>「たったそれだけ……途方もない気持ちになりますね」</p>
<p>「しかも、性質があまりわかってない。だから、探すのはすごく大変」</p>
<p>そう言うと篠澤さんは、ホワイトボードの真ん中に箇条書きを始めた。</p>
<list current_no="1" total_no="3">速度: ビリアル化（重力束縛）の仮定の下で、大まかに見積もれる。さらに地球自体の運動も考えると、観測者は運動方向と逆向きに『ダークマターの風』を受ける。</list>
<list current_no="2" total_no="3">質量: 素粒子ダークマターの候補は、質量範囲に<inlineequation><Image href="file://images/_review_math/_gen_d59eced1ded07f84c145592f65bdf854358e009c5cd705f5215bf18697fed103.pdf" type="inline"/></inlineequation>桁ほどの幅がある。複合粒子や天体スケールの候補なら、さらに重い可能性も。</list>
<list current_no="3" total_no="3">相互作用: 重力以外にどの程度・どんな相互作用を持つのかは、まだ不明。</list>
<p>「わかっていないことだらけで頭が痛い……。これ、どうやって探すんです？」</p>
<p>「ふふっ、ままならないね」</p>
<p>俺が頭を抱える横で、篠澤さんは嬉しそうに笑う。</p>
<note><p><b>◆束縛系プロデューサー</b></p>
<p>「物理のぶの字も知らないよわよわなプロデューサーでも、円運動の公式くらい、覚えてるよね」</p>
<p>「いつものリベンジかというくらい理不尽な言われようですが、全面的に同意します。円運動くらいなら、高校でやりましたね」</p>
<p>「私も円運動する星と一緒。プロデューサーに束縛されて、自由な時間もない。かわいそう」</p>
<p>「人聞きの悪いこと言わないでくださいよ⁉　篠澤さんが人並みに練習をこなせれば、もっと早く帰れるんですからね」</p>
</note>
<h2>1.2　ダークマターの直接探索</h2>
<?dtp level="2" section="1.2　ダークマターの直接探索"?>
<p>「ダークマター探しはすごく難しいけど、いくつか方法が試されてるよ。なかでも面白いのが『直接探索』（レビュー：<span type="bibno">[2] </span>）──身の周りにあるダークマターを、研究室に置いた検出器で直接狙うやり方<footnote>宇宙の観測からダークマター由来の信号を探す『間接探索』や、加速器でダークマターを作って探す方法もあるけど、ここでは触れない、よ。</footnote>」</p>
<p>「待ってください。相互作用がわからないなら、検出器の作りようがないのでは？」</p>
<p>「それはそう。だから、考えられる可能性を全部当たる」</p>
<p>「……いま、なんと？」</p>
<p>「全部探す。候補はたくさんあるから、質量や相互作用ごとに、いろんな実験を動かして当たる」</p>
<p>「なかなかの執念ですね」</p>
<p>「趣味に費やす熱量、だと思う。こういう研究を突き動かす源。私がアイドルになるのと同じ」</p>
<p>「ずるいですね。そう言われると、応援せざるを得ません」</p>
<p>「ふふっ、わかってる。じゃあ今日は、直接探索の手法を簡単にレビューしよう。あわせて、物理の他分野との関係にも触れてみる」</p>
<p>ホワイトボードの右端に、いくつか項目を箇条書きする。なるほど、今日の『お品書き』はこれか。</p>
<list current_no="1" total_no="4">原子核散乱</list>
<list current_no="2" total_no="4">電子散乱</list>
<list current_no="3" total_no="4">集団励起モード</list>
<list current_no="4" total_no="4">量子センサー</list>
<h4>原子核散乱</h4>
<?dtp level="4" section="原子核散乱"?>
<p>「最初は、ダークマターとぶつかって跳ね返された原子核を探すやり方。ここで問題。原子核散乱で探せるダークマターは、どのくらいの重さのものだと思う？」</p>
<p>「本当に答えを期待してます？　全く見当もつきません」</p>
<p>「簡単な想像でわかる。まず軽すぎると、ぶつかってもエネルギーが足りず原子核を動かせない」</p>
<p>「なるほど、ビー玉をぶつけても車は動きませんからね。それなら逆に、重ければ重いほどいいんでしょうか？」</p>
<p>「エネルギー的にはそう。でも、観測から質量密度が決まってる。重いほど個数が少なくなるから、見つけづらい」</p>
<p>「では、その間に一番見つけやすい質量があるわけですね」</p>
<p>「うん。原子核散乱は、原子核と同程度の質量に最も感度が出る。理論的にもその辺りに有力候補<footnote>Weakly-interacting massive particle (WIMP)と呼ばれる候補。超対称性標準模型などを考えると、自然に出てくるよ。</footnote>があるから、実験は早くから活発だった」</p>
<p>そこまで言って、篠澤さんは俺にペンを向けた。</p>
<p>「じゃあ、次の練習問題。ダークマターが私の体と衝突する頻度を求めてみよう。まだギリギリ見つかっていないところ<span type="bibno">[3] </span><span type="bibno">[4] </span><span type="bibno">[5] </span>を想定して──」</p>
<list current_no="1" total_no="2">質量 <inlineequation><Image href="file://images/_review_math/_gen_374baf9cda5f4e4fd3cd309e0976387d48d5ec328373c32bf2e2f2de0837d9b1.pdf" type="inline"/></inlineequation></list>
<list current_no="2" total_no="2">陽子・中性子との散乱断面積 <inlineequation><Image href="file://images/_review_math/_gen_ef403bf431a7df9ffc0b2bbb2c2074363dce1f95eb114f7bb6d6fb337b364b0f.pdf" type="inline"/></inlineequation></list>
<p>書かれた記号を見て目を白黒させていると、篠澤さんが補足してくれる。</p>
<p>「ここで、<inlineequation><Image href="file://images/_review_math/_gen_389145343df71406c39018d808e9971ee4c958d668bdfca583467be784999768.pdf" type="inline"/></inlineequation>はエネルギーや質量の単位<footnote>有名なアインシュタインの方程式<inlineequation><Image href="file://images/_review_math/_gen_f2be93acefe998252eb1b8ddbcbfe428f547b60689dfea6eecc3886d21d73dee.pdf" type="inline"/></inlineequation>でエネルギーと質量は関係付くよ。光速<inlineequation><Image href="file://images/_review_math/_gen_2e7d2c03a9507ae265ecf5b5356885a53393a2029d241394997265a1a25aefc6.pdf" type="inline"/></inlineequation>を<inlineequation><Image href="file://images/_review_math/_gen_6b86b273ff34fce19d6b804eff5a3f5747ada4eaa22f1d49c01e52ddb7875b4b.pdf" type="inline"/></inlineequation>とする自然単位系では、さまざまな量を共通の単位<inlineequation><Image href="file://images/_review_math/_gen_389145343df71406c39018d808e9971ee4c958d668bdfca583467be784999768.pdf" type="inline"/></inlineequation>で測れて、かんたん。</footnote>。散乱断面積は──ビー玉をふたつぶつけるとき、断面積が大きいものほどぶつかりやすい。それと同じで、素粒子同士の衝突しやすさを表すのが、散乱断面積」</p>
<p>「なるほど、なんとなくわかりました。じゃあ続きを……どうしました？」</p>
<p>篠澤さんが腕を上げたまま固まっている。何かを思い悩んでいるように見えた。</p>
<p>「どうしよう、プロデューサー。このままだと数式を書くことになっちゃう」</p>
<p>「いいんじゃないですか？　覚悟はできてますよ」</p>
<p>「でも、一般向けの本で数式を書くと売り上げが落ちるって」</p>
<p>「……これまでのページを見るに、もう手遅れじゃないですか？」</p>
<p>「……それはそう」</p>
<p>篠澤さんは納得したようにうなずくと、ホワイトボードにすらすらと数式を書き始めた。</p>
<displayequation><Image href="file://images/_review_math/_gen_9a66598dac94a1a9b542512234f33e31579c143a389252ba4f4cf1e6a4d82d72.pdf"/></displayequation>
<p>「まず、ダークマターの存在量<inlineequation><Image href="file://images/_review_math/_gen_acdb1aa91ad9723d25532a89a9f9c84a677bcb86227f18c94525556310b0aba3.pdf" type="inline"/></inlineequation>を<inlineequation><Image href="file://images/_review_math/_gen_62c66a7a5dd70c3146618063c344e531e6d4b59e379808443ce962b3abd63c5a.pdf" type="inline"/></inlineequation>で割って、体積あたりの個数<inlineequation><Image href="file://images/_review_math/_gen_1b16b1df538ba12dc3f97edbb85caa7050d46c148134290feba80f8236c83db9.pdf" type="inline"/></inlineequation>を求める」</p>
<displayequation><Image href="file://images/_review_math/_gen_1cea35940e74a63f379bfd2dce1f69c9e24c5df3986c9a78c51227615c69be34.pdf"/></displayequation>
<p>「これにダークマターの速さ<inlineequation><Image href="file://images/_review_math/_gen_4c94485e0c21ae6c41ce1dfe7b6bfaceea5ab68e40a2476f50208e526f506080.pdf" type="inline"/></inlineequation>をかけたのが、フラックス<inlineequation><Image href="file://images/_review_math/_gen_f67ab10ad4e4c53121b6a5fe4da9c10ddee905b978d3788d2723d7bfacbe28a9.pdf" type="inline"/></inlineequation>。<inlineequation><Image href="file://images/_review_math/_gen_86a21c290849de0af1e07c2c2e931a61ca35f69a4c38b8866d6ebbac6973907e.pdf" type="inline"/></inlineequation>の紙を置いておくと、<inlineequation><Image href="file://images/_review_math/_gen_6b86b273ff34fce19d6b804eff5a3f5747ada4eaa22f1d49c01e52ddb7875b4b.pdf" type="inline"/></inlineequation>秒あたり<inlineequation><Image href="file://images/_review_math/_gen_0e9e3b5a0b16d53c47da0ea21dac9645fa5b5f1a97e6f52acb87dff00472d196.pdf" type="inline"/></inlineequation>個のダークマターが通過する」</p>
<p>「あれ、意外と多いですね。牛乳パック一つ分という話では？」</p>
<p>「ひとつひとつが軽いから」</p>
<displayequation><Image href="file://images/_review_math/_gen_2678ab27dc2b1925f06ac5f18dbd5dad51b7e30d2730cd663d6bf32c142311a8.pdf"/></displayequation>
<p>「私の中に陽子や中性子がたくさんあるから、総断面積はそれだけ大きくなる。体重<inlineequation><Image href="file://images/_review_math/_gen_08f271887ce94707da822d5263bae19d5519cb3614e0daedc4c7ce5dab7473f1.pdf" type="inline"/></inlineequation>を核子の重さ<inlineequation><Image href="file://images/_review_math/_gen_f32891d7dfdd471eafff1b569de3ee4741483f8bcd551e473f875da319f2445c.pdf" type="inline"/></inlineequation>で割って、<inlineequation><Image href="file://images/_review_math/_gen_9c3245dfb4ac54c1623a60e7b8d1fc07cb02eae1229435230c7dab5e71083a26.pdf" type="inline"/></inlineequation>にかける<footnote>本当は、重い原子核では核子の寄与が位相をそろえて加わって（コヒーレンス）、断面積が質量数の二乗で大きくなることがあるよ。プロデューサーには荷が重そうだから、今日は無視しよう。</footnote>」</p>
<p>「体重が重いほど有利になりますね。篠澤さん、もっと食べましょう」</p>
<p>俺の軽口を無言で受け流して、続きの数式に取り組む篠澤さん。</p>
<displayequation><Image href="file://images/_review_math/_gen_4eb89de0bd478e9f3b9c5aa3aad9d9ea26e2e1fe3032edf6e1b6761251bb4c2c.pdf"/></displayequation>
<p>「最後にフラックスと断面積を掛け合わせて、衝突頻度が求められる。つまり──百万年に一回くらい」</p>
<p>「少なっ！　やっぱり嘘なんじゃないですか、さっきの」</p>
<p>「ふふっ、起きちゃった。百万年に一度の奇跡」</p>
<p>「篠澤さんが無事にアイドルデビューできたことが、同じくらい奇跡だと言えるかもしれませんね」</p>
<p>「百万年に一人の逸材、だよ」</p>
<p>「……ある意味その通りですね。原子核散乱の実験でも奇跡が起こることを願うばかりです」</p>
<p>「実験では、キセノンなどの重い原子を大きな容器に充填する。衝突頻度は、もっとずっと大きいはず」</p>
<note><p><b>◆重い女</b></p>
<p>「結局、GeVってどのくらいの重さなんですか？」</p>
<p>「それは少し考えればわかる」</p>
<p>「……残念ながら、篠澤さんと違ってわからないから聞いているんです」</p>
<p>「水素原子<inlineequation><Image href="file://images/_review_math/_gen_3a39db7744095a3d89a43ca452e7564b611d2c82f109b5e85b83eca34fe27185.pdf" type="inline"/></inlineequation>が<inlineequation><Image href="file://images/_review_math/_gen_87170463ecd098eff91c3841e5972081d46b46c3b826125bfcc2f7de4c666988.pdf" type="inline"/></inlineequation>になることは知っているはず。水素原子の重さはほとんど陽子由来。幼稚園で習ったとおり、陽子一つはだいたい<inlineequation><Image href="file://images/_review_math/_gen_f560b64fb85a46f24d359cd7fa202970fb9111a5e09d05bb9affc0405f71610e.pdf" type="inline"/></inlineequation>だから……」</p>
<p>「待ってください、どの幼稚園の話をしてます？　子供ができたときの参考にさせてもらいます」</p>
<p>その言葉を聞いた篠澤さんは、なぜか頬を染めてこちらを見上げる。</p>
<p>「プロデューサー、気が早いよ」</p>
<p>「懲戒免職ものですよ、それ⁉　……ごほん。ええと、つまり結論は」</p>
<p>「<inlineequation><Image href="file://images/_review_math/_gen_3a39db7744095a3d89a43ca452e7564b611d2c82f109b5e85b83eca34fe27185.pdf" type="inline"/></inlineequation>はアボガドロ定数、<inlineequation><Image href="file://images/_review_math/_gen_80b525d3c56e43f4016ad55a6f6efede1d03cc10a74ecdd9c439e331c093707b.pdf" type="inline"/></inlineequation>個。だから、<inlineequation><Image href="file://images/_review_math/_gen_fd2ecddd48ca8b1fb64de51b89dd0cdcf4d6e7c5d1a23a17cb57d0de952d7992.pdf" type="inline"/></inlineequation>。私の体重なら、<inlineequation><Image href="file://images/_review_math/_gen_71e1bf883c3ea04a89eca893a5892d5ee2969431475ec4ba34128336dd10e0e7.pdf" type="inline"/></inlineequation>くらい」</p>
<p>「その手には乗りませんよ。篠澤さんはやはり、もっと食べるべきです」</p>
<p>「プロデューサーの鬼。そういうところも好き」</p>
</note>
<h4>電子散乱</h4>
<?dtp level="4" section="電子散乱"?>
<p>「原子核散乱を使って、人類は何十年もダークマターを探してきた。でもいまのところ、何も見つかっていない」</p>
<p>「ままなりませんね」</p>
<p>「ならない。だけど原子核で探せるのは、<inlineequation><Image href="file://images/_review_math/_gen_d59eced1ded07f84c145592f65bdf854358e009c5cd705f5215bf18697fed103.pdf" type="inline"/></inlineequation>桁もある質量範囲の上の方、数桁だけ。だから、もっと軽い側も探そうという流れが生まれた」</p>
<p>「ダークマター界隈にもそういった流行があるんですね」</p>
<p>「ここで問題。軽いダークマターを探すには、何を使えばいい？」</p>
<p>首をわずかに傾け、まっすぐな視線で問いかけてくる篠澤さん。頭に引っかかって止まっていた一筋の髪が、重力に引かれてはらりと垂れた。</p>
<p>「さっきの話を応用すると、軽い粒子との散乱を考えればよくて……電子、とかはどうでしょう？」</p>
<p>「すごい。予想だにしない完璧な答え」</p>
<p>「すごいでしょう。ダークマター探索、完全に理解しました」</p>
<p>「それ、ダニング＝クルーガー効果っていう、初学者がはまりがちなやつ。本当はまだ理解できていないことだらけなのに、全部理解した気になっちゃう」</p>
<p>「……すみません、調子に乗りました。原子核と電子の違いはきっと、重さだけではないのですよね」</p>
<p>「そう。物質中の電子の性質は、その物質自体の性質を左右するから。ダークマターを記述する素粒子理論の知識に加えて、物性物理の知識を応用して、物質中の電子のふるまいを理解する必要がある」</p>
<p>言いながら簡単なベン図を描き、交わった部分にダークマターと書き添える。</p>
<p>「電子と物質の性質の関係が、いまいちピンと来ませんね」</p>
<p>「いわゆるバンド理論。物質中の電子は、持ち得る運動量やエネルギーが決まってる。教室に椅子が並んでいるようなもの。椅子にはひとつの電子しか座れないし、すべての電子がどれかの椅子に座らないといけない」</p>
<p>三種類の図を描いた篠澤さんは、そのそれぞれを指しながら説明を加えた。</p>
<Image href="file://images/mayoi_darkmatter/band_gap.pdf" scale="0.9"/>
<img-caption>図1.1　物質中の電子。白四角とバツ印がそれぞれ、空いた椅子と埋まった椅子。</img-caption>
<list current_no="1" total_no="3">金属: 椅子に空きがある状態。外から電場がかかると、電子は別の椅子へ移動しやすい。このとき全体として電子の運動が生じ、電流が流れる。</list>
<list current_no="2" total_no="3">絶縁体: 教室内の椅子がすべて埋まっている状態。電子が移動するには、隣の教室まで廊下（ギャップ）を越えるエネルギーが必要で、電流が流れにくい。</list>
<list current_no="3" total_no="3">半導体: 二者の中間。椅子は埋まっている一方、隣の教室までの距離が近いので、比較的小さなエネルギーで電流が流れる。</list>
<p>「最初に埋まっている椅子を価電子帯、空いている椅子を伝導帯と呼んで、電子が伝導帯に移ると電流が流れる」</p>
<p>「だから、電流の流れやすさは電子の移動しやすさで決まる、と。ちょっとわかってきました」</p>
<p>そのとき、廊下で騒がしい物音がした。初めは騒音にしか聞こえなかったそれは、近づくにつれて人の声の形がはっきりとしてくる。</p>
<p>「お姉ちゃ～～～～～～～～～～～～～～～～～～～～～～～ん！」</p>
<p>ドップラー効果を伴ってドタドタと過ぎ去ったあと、わずかに奇妙な沈黙が降りた。</p>
<p>「……あれが、伝導帯にいる電子の状態」</p>
<p>「たしかに、初めて花海さん……佑芽さんに会ったとき、俺の中にも電流が走りました。あれは篠澤さんとは別種の衝撃でしたね」</p>
<p>目線をホワイトボードに戻す篠澤さん。</p>
<p>「ダークマター探索には、特に半導体が便利」</p>
<p>「半導体というと、パソコンの部品なんかに使われるやつですよね」</p>
<p>「そう。小さなエネルギーで電子を伝導帯に移せるのが、半導体のメリット。絶縁体だと必要なエネルギーが大きすぎるし、逆に金属だとダークマター以外のノイズに弱い」</p>
<p>「金属と絶縁体のいいとこ取りをしたわけですね」</p>
<p>「さっきプロデューサーが言ったみたいに、半導体にはパソコンとかの工学応用がたくさんある。だから技術が確立していて、電子信号の読み取りもやりやすい」</p>
<p>そう言った篠澤さんは、床に置いた鞄からスマホを取り出し、俺に向けた。一閃。唐突なフラッシュが視界を白に染める。</p>
<p>「まぶしっ！　なんですか急に！」</p>
<p>「デジタルカメラを例に挙げると、元々は光検出にCCDイメージセンサを使っていた。同じ原理でダークマターも探せる<span type="bibno">[6] </span><span type="bibno">[7] </span>。電子が伝導帯に移動したら、電圧操作で電流を制御して、信号を外部に取り出せる」</p>
<p>カメラが起動したままのスマホを片手に、破線の矢印を書き加える。</p>
<p>「へえ、そんな身近な技術がダークマターを探すのに使えるなんて、面白いですね」</p>
<p>「……まあ、最近のカメラはCMOSイメージセンサを使う方が主流なんだけど」</p>
<p>手元に視線を落とした篠澤さんが、スマホの画面を見てふわりと笑った。</p>
<p>「ふふ、プロデューサー情けない顔してる。待ち受けにしちゃお」</p>
<p>「気まずいからやめてください！　最初からその写真を撮りたかっただけですよね！」</p>
<note><p><b>◆ドヤ顔が可愛い系アイドル</b></p>
<p>「……たくさんしゃべったら、お腹空いて倒れそう」</p>
<p>「相変わらずス●ランカーですね。食べる量が少ないからですか、急に低血糖の症状が出るのは」</p>
<p>言いながら、鞄をあさる。指先で探り当てたそれを、篠澤さんに差し出した。</p>
<p>「ばなな」</p>
<p>「栄養満点です。量を食べられない人向きですよ。……どうかしましたか？」</p>
<p>篠澤さんが、受け取ったバナナをしげしげ眺めていた。</p>
<p>「懐かしい。海外の大学にいたとき、よく食べてたから」</p>
<p>「そういえば、その頃の話を聞いてないです。食べ物には困らなかったんですか？」</p>
<p>「バナナラウンジっていう、バナナ取り放題の部屋があった。あとはイベントで出るフリーピザとかで生きてた、よ」</p>
<p>「それだけで足ります？　ちゃんと栄養は摂れていましたか」</p>
<p>すると、篠澤さんは腰に手を当てて、謎のドヤ顔で宣言した。</p>
<p>「一日、三本くらい」</p>
<p>「バナナ以外も食べてますよね⁉　……いえ、ここで言っても仕方ないことでした」</p>
<p>「うん、いまなら四本は食べられる」</p>
<p>「バナナ以外も食べましょうね‼」</p>
</note>
<h4>集団励起モード</h4>
<?dtp level="4" section="集団励起モード"?>
<p>「まあ百歩譲って写真を撮るのはいいですけど……気をつけてくださいね」</p>
<p>「何を？」</p>
<p>「授業中に写真を見ていて、スマホを没収された例がありますから」</p>
<p>プロデューサー科の同期から聞いた話を思い出す。担当アイドルに写真を撮られ、没収されたスマホからそれが見つかって面倒なことになったらしい。</p>
<p>たしか、彼の担当アイドルは篠澤さんと同期の、月村──</p>
<p>「失礼します」</p>
<p>「あ、手毬だ」</p>
<p>そのとき、ノックの音とともに見覚えのある顔がのぞいて、俺は思わず飛び上がった。</p>
<p>腰あたりまで伸びた髪をなびかせながら、一人の女子生徒が入室してくる。スマホ没収事件の登場人物の一人、月村手毬だ。</p>
<p>「……おや、もう次の予約の時間ですか？」</p>
<p>内心の動揺を隠して尋ねると、月村さんは首を横に振った。</p>
<p>「いえ、まだです。ちょっとレッスン前に確認したいところがあって。隅の方でいいので、使わせてもらえないかと……なんですかこれは？」</p>
<p>ホワイトボード一面の数式や図に気づいて、月村さんが露骨に眉をひそめる。</p>
<p>「ダークマターというものについて、篠澤さんに教わっているところです。もうしばらく休憩しているので、使ってもらって構いませんよ」</p>
<p>「手毬、手毬。いっしょにダークマター探さない？」</p>
<p>「相変わらず馴れ馴れしいな。そんなわけのわからない誘いには乗らないから」</p>
<p>「さっき篠澤さんを見ていて思ったのですが、こういう議論は頭を使うので……けっこうカロリーを消費しますね」</p>
<p>「やります！」</p>
<p>……本当にわかりやすい人だなあ。
</p>
<p><b>＊＊＊</b>
</p>
<p>「プロデューサーは、ライブ中に会場の外で音漏れを聞くこと、ある？」</p>
<p>「担当アイドルの控え中に、別の仕事の電話が来たら外に出ますね。それが何か？」</p>
<p>「会場の外だと、ライブの音はどういう風に聞こえる？」</p>
<p>「当然ですけど、会場の中とは全く違う聞こえ方をしますね。低音が強調されて、ずんずんと響いてくる感じと言いますか」</p>
<p>「そう。それが重要な波の性質。音は空気の密度の波で、波長によって伝わりやすさが決まる。例えば──手毬の“Luna say maybe”って、最高音はどれくらい？」</p>
<p>「hiD♯」</p>
<p>「ってことはちょうどhiAとhihiAの中間だから、周波数は<inlineequation><Image href="file://images/_review_math/_gen_8b47a21c53ffb54bc9cab2b2ba2adec9ccfc4ef74fda9f14ddff47958041263e.pdf" type="inline"/></inlineequation><footnote>hiAはよくチューニングに使われて、<inlineequation><Image href="file://images/_review_math/_gen_d86241ea1e1553de4d24bfad9f59b7f1b23fc0a5276cd3aebe56ab1007aba30d.pdf" type="inline"/></inlineequation>周辺に音が取られるね。これを基準に、周波数の2倍幅を1オクターブと呼ぶ。ピアノの音に対応する十二平均律は、1オクターブをログ等間隔で12分割する。だからhiD♯は6音下のhiAよりも<inlineequation><Image href="file://images/_review_math/_gen_a546f4efcaafb7d8286765e64a4eaea85540f66d4119f14527df57d47206d0b8.pdf" type="inline"/></inlineequation>倍大きな周波数を持つけど、非有理数倍の周波数ではきれいにハモりづらい。響きを優先する場合は、和音の周波数が簡単な有利数倍になるような純正律を採用する、よ。</footnote>。……手毬、<inlineequation><Image href="file://images/_review_math/_gen_1a948f1b4374f4e3f02501c7feb43784021718a93c1ed5f9f19adf357bb2d20e.pdf" type="inline"/></inlineequation>かける<inlineequation><Image href="file://images/_review_math/_gen_e3f6959781c353c201d378e02d9da532601673e08a1706fa15a5ebbd9ea1bd36.pdf" type="inline"/></inlineequation>は？」</p>
<p>「は？　なんで私がそんなこと」</p>
<p>「カロリー消費のため。頑張って」</p>
<p>篠澤さんが差し出したペンを、月村さんは悔しそうな表情で受け取った。ホワイトボードの隅の方で筆算を始める。</p>
<p>「手毬が計算してる間に先に進めよう。だいたい<inlineequation><Image href="file://images/_review_math/_gen_964e4c53e5372fec6c3e4ae170e75e45c20eaf35985da553acd24bd97bfb6304.pdf" type="inline"/></inlineequation>で、音速は<inlineequation><Image href="file://images/_review_math/_gen_6b66dafa78322cd0446cac0ab0e79153326bb4db70f538b03da08341c4a1d6ca.pdf" type="inline"/></inlineequation>。簡単のために<inlineequation><Image href="file://images/_review_math/_gen_0ffa7fb1a4fe59af4df36aede4dca102c76ae702c3e99f8aa3bf97b80edfae19.pdf" type="inline"/></inlineequation>として──」</p>
<displayequation><Image href="file://images/_review_math/_gen_918330976d555eeee9d1ee66de9705fc6d0b54d3427aeddb86b0c180ab28d97d.pdf"/></displayequation>
<p>「一回振動する間に波が進む距離を計算すれば、波長はこの通り計算できる」</p>
<p>「<inlineequation><Image href="file://images/_review_math/_gen_683d098205b11550f2d71016c82c4377a96c9f808e132f83f15ba9bd058c7b20.pdf" type="inline"/></inlineequation>！　<inlineequation><Image href="file://images/_review_math/_gen_1a948f1b4374f4e3f02501c7feb43784021718a93c1ed5f9f19adf357bb2d20e.pdf" type="inline"/></inlineequation>かける<inlineequation><Image href="file://images/_review_math/_gen_e3f6959781c353c201d378e02d9da532601673e08a1706fa15a5ebbd9ea1bd36.pdf" type="inline"/></inlineequation>は、<inlineequation><Image href="file://images/_review_math/_gen_683d098205b11550f2d71016c82c4377a96c9f808e132f83f15ba9bd058c7b20.pdf" type="inline"/></inlineequation>！」</p>
<p>「ありがとう。じゃあ、<inlineequation><Image href="file://images/_review_math/_gen_9644294ac4ffb3091eef01219b3fe4fe467f05890cc56af961dce68fddbb7704.pdf" type="inline"/></inlineequation>割る<inlineequation><Image href="file://images/_review_math/_gen_683d098205b11550f2d71016c82c4377a96c9f808e132f83f15ba9bd058c7b20.pdf" type="inline"/></inlineequation>は？　最初の二桁だけでいいよ」</p>
<p>「くっ……カロリーのため‼」</p>
<p>「ところで“TMR”と書いてあるのは、『手毬』という意味ですか？」</p>
<p>「そう」</p>
<p>筆算の記号を書き終えて忙しそうな月村さんににらまれた。篠澤さんはそれを意にも介さず、ホワイトボードに向き直って解説を続ける。</p>
<p>「ベースの方は、三オクターブくらい低い<inlineequation><Image href="file://images/_review_math/_gen_22a3e7106326b88077276c1c751692e5fda26e1398748904ec9ac3f15ca7547e.pdf" type="inline"/></inlineequation>とすると」</p>
<displayequation><Image href="file://images/_review_math/_gen_72e6e3c5dedcfab0bca59f9a1cb63a1aafba6c079a1ca9166d1e9286de2626d9.pdf"/></displayequation>
<p>「0.55！」</p>
<p>「うん、<inlineequation><Image href="file://images/_review_math/_gen_168f0b8488eb0e3379d257c87b93f6b4471f5c6500a2a441a113b716efedbd87.pdf" type="inline"/></inlineequation>は<inlineequation><Image href="file://images/_review_math/_gen_c7f8f37395663ba0d1fb16c06c8a1f6bdabdcbfba5ce14900781a76c2b12bd87.pdf" type="inline"/></inlineequation>、そのくらいだと思う。じゃあ次は──」</p>
<p>「ちょっと！　私が計算しなくてもどんどん先に進んでるじゃない！」</p>
<p>ホワイトボードの式に気づいた月村さんが叫ぶ。</p>
<p>「検算、ありがとう」</p>
<p>「ともかく、低音と高音でどのくらい波長が違うのかはわかりました」</p>
<p>「うん。そして波長は波の空間解像度だから、回折が起きる。波は、波長より小さい障害物を回り込める」</p>
<p>「なるほど。高音域と低音域の波長がそれぞれ<inlineequation><Image href="file://images/_review_math/_gen_40f6fbd1af46adaf25ed969ae3671acf3289febb022f2bc49fb0c69bf2fb6f0b.pdf" type="inline"/></inlineequation>と<inlineequation><Image href="file://images/_review_math/_gen_17ebb481c15a14271176dadf6c79fa23308cd7fb63a788424c3ac36219ae2f10.pdf" type="inline"/></inlineequation>でしたね。すると、<inlineequation><Image href="file://images/_review_math/_gen_478875a1fe001c848c026f1c355083541b6973288f7016a390c9b3bbc66066a2.pdf" type="inline"/></inlineequation>くらいの障害物、例えば柱や人間が多い場所だと……」</p>
<p>「短波長の高音は回り込めずに吸収・反射されやすい。だから外では低音が強調されて聞こえる。スピーカーの指向性とか副次要因もあるけど、基本は同じ議論」
</p>
<p><b>＊＊＊</b>
</p>
<p>「それで？」</p>
<p>説明を咀嚼していると、明らかに不機嫌そうな月村さんが割り込んでくる。</p>
<p>「私に小学生みたいな計算をさせて、何のつもり？　ダークマターの話じゃなかったの？」</p>
<p>「そうですね。この先どうつながるのか、俺も気になっています」</p>
<p>それを聞いた篠澤さんはペンを置き、こちらに向き直る。</p>
<p>「ライブ会場の例は、音の波の話。量子力学では、すべての物は粒子であり同時に波。今度はダークマターの波を考えたい」</p>
<p>「波と粒子の二重性、ですね」</p>
<p>「ダークマターのド・ブロイ波長は運動量に反比例する。軽いほど運動量が小さいから、波長は長い」</p>
<p>「軽い方がさっきの例の低音域に対応しますね。今回も空間解像度が問題なんでしょうか？」</p>
<p>月村さんが何か言いたげに視線を寄越す。……なんで篠澤さんと会話が成立するのかって？　俺にもわからない。プロデュースを続けるうちに、いつの間にか慣れてしまったのだ。</p>
<p>「うん。ダークマターが電子より軽いと、波長は原子間隔より長くなる。すると一つ一つの原子核や電子を見分ける空間解像度がなくなって、代わりにそれらの集団にまとめて作用する。結果として集団励起モードを生じる」</p>
<p>「具体的には？」</p>
<p>「例えばフォノン。固体中の原子核の振動。ライブ会場のウェーブみたいな動き。振動は最終的に熱になるから、超伝導転移センサー（TES）のような高精度な温度計で信号を拾える<span type="bibno">[8] </span><span type="bibno">[9] </span><span type="bibno">[10] </span>。わかった、手毬？」</p>
<p>つられて横を見ると、月村さんは虚空を見つめて固まっていた。もう限界らしい。</p>
<p>「ちなみに、物質中を伝わる音波もフォノンの一種。だからフォノンで探すのは、ダークマターの音を聞く実験でもある、よ」</p>
<p>篠澤さんの言葉に想像力をかき立てられる。宇宙から飛んでくる目に見えない粒子が、人知れず物質と衝突し、かすかな音を奏でる。人類はその音に耳を澄ます──</p>
<p>ぐぎゅるぎゅる。静寂の中、隣から気の抜ける音が響いた。</p>
<p>「月村さん……」</p>
<p>「そんな目で見ないで！　話はさっぱりなのに、お腹だけ空いてきたの。悪い⁉」</p>
<p>「ある意味、目標達成では？」</p>
<p>「レッスン前なのに、何か食べたくなるじゃない！」</p>
<p>勢い任せに立ち上がった月村さんに、篠澤さんがペンを差し出す。ひったくった月村さんは、ホワイトボードに何事かをガシガシと書き殴り、荒々しい足音で出て行った。</p>
<p>……ダンスの確認、しなくてよかったのかな？</p>
<p>控えめに描かれたベン図の横、乱暴な筆跡で『とんかつ』。それを見ながらそう思った。</p>
<note><p><b>◆「まるでエベレスト登山ですわ～⁉」</b></p>
<p>「そういえば篠澤さん。以前の指示どおり、マシントレーニングもこなしていますか？」</p>
<p>「ウォーキングマシンとか？」</p>
<p>「その呼び方は若者には許されません。通称は『ランニングマシン』です」</p>
<p>「ちゃんと毎日歩いてる。でも、あのマシン、全然面白くない」</p>
<p>「面白さを求めるものでもないですが……具体的にどのあたりが？」</p>
<p>「負荷がランダムで変わるモードがあるけど、シード値が固定で毎回同じパターンしか出ない」</p>
<p>「なるほど。俺もたまに使いますけど、全然気づきませんでした」</p>
<p>「一定の確率で最高負荷が唐突に来る『確変鬼畜モード』があってもいいと思う」</p>
<p>「……それは安全性の懸念で実装されないんだと思いますけどね」</p>
<p>「だから、いつも使うマシンは私好みにカスタムした」</p>
<p>「学園の設備をハッキングしたらダメですよ⁉」</p>
<p>「この間、千奈が間違って鬼畜モードに入っちゃって」</p>
<p>「すぐ元に戻してください！」</p>
</note>
<h4>量子センサー</h4>
<?dtp level="4" section="量子センサー"?>
<p>「ここまでの話はわかった？」</p>
<p>「ええ、雰囲気はつかめました。いろんな探索手法があるんですね」</p>
<p>「ちゃんと伝わったみたいでよかった。……ふぅ」</p>
<p>「しゃべり疲れましたか？」</p>
<p>「ううん。うまくいきすぎて、つまらなくなった。プロデューサー、いつものよろしく」</p>
<p>「そう言われましても、教師がよくて本当にわかりやすいので……。ところで、質量範囲<inlineequation><Image href="file://images/_review_math/_gen_d59eced1ded07f84c145592f65bdf854358e009c5cd705f5215bf18697fed103.pdf" type="inline"/></inlineequation>桁のうち、これまでの方法でカバーできるのはどのくらいですか？」</p>
<p>「マイクロ波領域を下回ると難しくて……<inlineequation><Image href="file://images/_review_math/_gen_f5ca38f748a1d6eaf726b8a42fb575c3c71f1864a8143301782de13da2d9202b.pdf" type="inline"/></inlineequation>桁くらい？　ままならないね。……そう、その調子」</p>
<p>「まだ半分も探せていないじゃないですか！　残りの領域をどうするのか、俺でもわかるようにしっかり説明してください」</p>
<p>「すごくいい。研究そのものより、プロデューサーがわかるように説明する方が難しい。困難な仕事はとても楽しい」</p>
<p>「篠澤さんよりも先に俺が泣きそうですけど、本当にこれであってます？」
</p>
<p><b>＊＊＊</b>
</p>
<p>「最後に、量子センサーでの探索について。軽い領域を中心に、応用が広がっている、よ」</p>
<p>「それじゃあこれまでのように、量子センサーの強みを説明してもらいましょうか」</p>
<p>「量子センサーは、量子性が強い物理系で信号を拾うセンサー。例えば量子コンピューターの超伝導量子ビットを流用する。メリットは──」</p>
<list current_no="1" total_no="3">状態操作と組み合わせて高感度プロトコル開発（ラムゼー干渉、スピンエコーなど）</list>
<list current_no="2" total_no="3">量子資源で感度向上（量子もつれ、スクイージングなど）<footnote>独立試行の感度限界は標準量子限界（SQL）と呼ばれる。量子もつれやスクイージングを使うと、SQLを上回るハイゼンベルク限界まで到達しうる、よ。</footnote></list>
<list current_no="3" total_no="3">将来的には量子計算・最適推定と統合可能（データ処理や読み出しの最適化）</list>
<p>「このメリットを活かすには量子情報の知識が要る。状態を作り、正しい読み出し方法を設計する必要があるから」</p>
<p>ホワイトボードの左上に残っていたベン図に、『量子情報』という円が書き加えられる。三つの円が交わった領域を指して、篠澤さんは続けた。</p>
<p>「最近のダークマター探索はこんな風に、いろいろな分野の交差点になってる」</p>
<p>「まさに集合知、いいですね」</p>
<p>思わず感心した声を漏らすと、篠澤さんは軽くうなずいた。</p>
<p>「簡単な例として、ラムゼー干渉を考える。コマを想像して。止まりかけると、軸がぐるぐる回るよね」</p>
<p>「懐かしいですね。ベイ●レードとか、よく遊んでいましたよ」</p>
<p>「あれは歳差運動。重力トルクで軸が回る。無重力で回すと、軸は回らず、まっすぐなまま止まる。つまり、回るコマ＝重力センサーとも言える」</p>
<p>「面白い考え方です。……待ってください、篠澤さん。子供の頃からそんなことを考えて遊んでいたわけではないですよね」</p>
<p>「……ラムゼー干渉も同じ。量子センサーを所定の状態に置き、歳差を測ることで信号を検出する」</p>
<p>「コマの例と量子センサー、篠澤さんの中ではつながっているんでしょうけど……もう少し直感的に理解できないでしょうか？」</p>
<p>「そう言われると思った。量子ビットの状態は『ブロッホ球』で表せる。きっとそれが、プロデューサーの求めているもの、だよ」</p>
<p>背を向けた篠澤さんが、よどみなく図を描き始める。二人の息の合った以心伝心ぶりに、感動さえ感じる俺だった。</p>
<Image href="file://images/mayoi_darkmatter/Bloch_sphere.pdf" scale="0.5"/>
<img-caption>図1.2　ブロッホ球</img-caption>
<p>「見て。ここに球がある。これがブロッホ球」</p>
<p>篠澤さんはホワイトボードに丸を描く。補助線を引くと、それは三次元の球になる。</p>
<p>「普通のコンピューターも量子ビットも、まず0と1が基本。図の上で0はここ──」</p>
<p>地球儀で言うところの北極を指し示す、篠澤さんの細い指。</p>
<p>「そして1はここ」</p>
<p>白い指で南極を指す。</p>
<p>「だから普通のコンピューターは、球上のこの二点しか表せない」</p>
<p>そう言いながら、太い実線の矢印を書き加える。</p>
<p>「一方で、量子ビットでは状態の重ね合わせが許される。数式で書くと、」</p>
<displayequation><Image href="file://images/_review_math/_gen_d91e7ea4f1433f096902a30cc2273c784fb315fbd566ef175253cd9753df72e5.pdf"/></displayequation>
<p>「ここで使ったふたつのパラメーター、<inlineequation><Image href="file://images/_review_math/_gen_2b4af44cb17349bb9452292a447fe70d48c9ce08e68dd2f74e9628cf8ac625b8.pdf" type="inline"/></inlineequation>と<inlineequation><Image href="file://images/_review_math/_gen_10ce0200b450ea955833553e717821c7721818b8a95cffd7e54b46e08918b512.pdf" type="inline"/></inlineequation>が図の球座標に対応する。つまり──」</p>
<p>数式に現れたのと同じ記号を、図にも書き加える。</p>
<p>……正直、篠澤さんの言うことはいつも三割もわからない。でも、それでいい。俺の役割は、すべてを理解することじゃない。</p>
<p>篠澤さんと目が合い、大きくうなずく。楽しそうに語る彼女が、楽しく話し続けられること。それが、俺の──</p>
<p>「例えば、量子ビットの状態を球上のこの点に選ぶと、」</p>
<p>破線の矢印が一本、彼女の表情はやっぱりどこか楽しげだ。</p>
<p>「<inlineequation><Image href="file://images/_review_math/_gen_594e519ae499312b29433b7dd8a97ff068defcba9755b6d5d00e84c524d67b06.pdf" type="inline"/></inlineequation>軸方向の信号があるとき、状態の歳差運動は点線で示した通り。信号を重力、破線矢印をコマの軸の方向と思うと、コマの運動と同じ」</p>
<p>「ああ、なるほど。俺にもコマの例との関係が見えてきました。すると、こういうことですね。今度はダークマターと量子ビットの相互作用を考えると──」</p>
<p>「同じ方法を軽いダークマターの検出にも使える。よかった、プロデューサーにもわかるように説明できた。……ふぅ」</p>
<p><bou>満足そうな表情で</bou>、<bou>つまらなそうにつぶやく</bou>。それを見て、俺も満足する。</p>
<p>──俺が篠澤さんを見限らなかったように、彼女も俺を見限らない。一歩ずつ、困難な道を進む。</p>
<p>「ここで説明したのは、量子センサーで信号を検出する手法の、ほんの一つ。ダークマターの性質によって、適した手法は変わるから、あらゆる方法を試し続けないといけない。<inlineequation><Image href="file://images/_review_math/_gen_d59eced1ded07f84c145592f65bdf854358e009c5cd705f5215bf18697fed103.pdf" type="inline"/></inlineequation>桁の範囲を探し尽くすためにも」</p>
<p>「ままならない道ですね」</p>
<p>「そう。とても険しくて、果ての見えない道。だから──」</p>
<p>言いかけて、篠澤さんは首をかしげた。何を言いかけたのか自分でも探るように、きょとんとした表情で固まる。たぶん、俺にはわかる。</p>
<h2>1.3　休憩終わり</h2>
<?dtp level="2" section="1.3　休憩終わり"?>
<p>「篠澤さん」</p>
<p>だから、思わず口を開いた。</p>
<p>「あなたは、全部うまくいってつまらないと言いましたよね。それが研究をやめてアイドルに転身した理由だと」</p>
<p>「うん」</p>
<p>「……だとしたら、いま物理を語るあなたが、どうしてそんなに楽しそうなんです？　ダークマターは候補だらけで、まだ見つかっていない。本当は気づいているんでしょう。──研究は、つまらなくなんかない。思っているよりずっと、ままならない」</p>
<p>「…………」</p>
<p>「あの篠澤広にすら、まだ解明できないことが世の中にはあふれている。全部うまくいってつまらないなんて、嘘です。それこそ、ダニング＝クルーガー効果です。困難な道があれば、嬉々としてそっちに行く──それが篠澤さんでしょう。アイドルと同じです。やりましょう、趣味で物理！」</p>
<p>考える前に口が走り、言い終わる頃には息が切れていた。篠澤さんは少し顔を伏せ、考え込む。沈黙が痛い。</p>
<p>「……ひどい。勉強や研究で、そんなこと言われたのは初めて」</p>
<p>……やばい、言い過ぎたか？</p>
<p>顔を上げる一瞬が、永遠みたいに長い。だが心配をよそに、彼女は頬を染めて微笑んだ。</p>
<p>「でも、わくわくしてきた。プロデューサーが、プロデューサーでよかった」</p>
<p>その笑顔に心を奪われていると、彼女はホワイトボードを回転させ、慌ただしく数式を消し始める。</p>
<p>「そうと決まれば、ゆっくりしていられない。続きを始めないと」</p>
<p>「続き⁉　一体何を……」</p>
<p>「場の量子論の基礎から始めて、現代素粒子論をプロデューサーにたたき込む。『趣味で物理』の相手として不足がないように、英才教育を──」</p>
<p>「ちょっとちょっと、待ってください！」</p>
<p>生き生き語る篠澤さんを遮った。</p>
<p>そりゃあ俺だって、楽しそうに話す彼女を見ているだけで胸が高鳴る。だけど俺はプロデューサーだ。この高鳴りは独占せず、大勢に届けられるように尽くすのが仕事。そうだろう？</p>
<p>「それ、全部説明するのにどのくらいかかりますか？」</p>
<p>「うーん……半日、くらい？」</p>
<p>だから俺は、『鬼のプロデューサー』に戻って、心臓の拍動に抗うように叫んだ。</p>
<p>「早くダンスレッスンに戻ってください！」</p>
<h2>参考文献</h2>
<?dtp level="2" section="参考文献"?>
<span type="bibno">[1] </span><bibitem id="bib-pdg">S. Navas et al. (Particle Data Group), Phys. Rev. D 110, 030001 (2024) and 2025 update</bibitem><span type="bibno">[2] </span><bibitem id="bib-DMDD">T. Lin, PoS 333 (2019) 009</bibitem><span type="bibno">[3] </span><bibitem id="bib-PandaX">Y. Meng et al. (PandaX-4T collaboration), Phys.Rev.Lett. 127 (2021) 26, 261802</bibitem><span type="bibno">[4] </span><bibitem id="bib-LZ">J. Aalbers et al. (LZ collaboration), Phys.Rev.Lett. 131 (2023) 4, 041002</bibitem><span type="bibno">[5] </span><bibitem id="bib-XENON">E. Aprile et al. (XENON collaboration), Phys.Rev.Lett. 131 (2023) 4, 041003</bibitem><span type="bibno">[6] </span><bibitem id="bib-DAMIC-M">K. Aggarwal et al. (DAMIC-M collaboration), Phys.Rev.Lett. 135 (2025) 7, 071002</bibitem><span type="bibno">[7] </span><bibitem id="bib-SENSEI">P. Adari et al. (SENSEI collaboration), Phys.Rev.Lett. 134 (2025) 1, 011804</bibitem><span type="bibno">[8] </span><bibitem id="bib-SuperCDMS">I. Alkhatib et al. (SuperCDMS collaboration), Phys.Rev.Lett. 127 (2021) 061801</bibitem><span type="bibno">[9] </span><bibitem id="bib-CRESST">G. Angloher et al. (CRESST collaboration), Phys.Rev.D 107 (2023) 12, 122003</bibitem><span type="bibno">[10] </span><bibitem id="bib-TESSERACT">C. L. Chang et al. (TESSERACT collaboration), arXiv: 2503.03683</bibitem></aid:doc>